blat_cli/__init__.py
blat_cli/cli.py
blat_cli/client.py
blat_cli/command.py
blat_cli/harvester/__init__.py
blat_cli/harvester/command.py
blat_cli/init/__init__.py
blat_cli/init/command.py
blat_cli/init_system/__init__.py
blat_cli/init_system/command.py
blat_cli/settings.py
blat_cli/utils.py
blat_cli-0.0.1.dist-info/LICENSE
blat_cli-0.0.1.dist-info/METADATA
blat_cli-0.0.1.dist-info/WHEEL
blat_cli-0.0.1.dist-info/entry_points.txt
blat_cli-0.0.1.dist-info/RECORD
