Metadata-Version: 2.1
Name: blat-cli
Version: 0.0.1
Summary: Command Line Interface to manage Blat AI agents
Author: Blat AI
Requires-Python: >=3.9,<3.13
Classifier: Programming Language :: Python :: 3
Classifier: Programming Language :: Python :: 3.9
Classifier: Programming Language :: Python :: 3.10
Classifier: Programming Language :: Python :: 3.11
Requires-Dist: httpx (>=0.27.0,<0.28)
Requires-Dist: playwright (>=1.41.2,<1.42)
Requires-Dist: pydantic-settings (>=2.2.1,<2.3)
Requires-Dist: pyyaml (>=6.0,<6.1)
Requires-Dist: typer (>=0.12.3,<0.13)
